README.md
setup.cfg
setup.py
py_expression_lib_opencv.egg-info/PKG-INFO
py_expression_lib_opencv.egg-info/SOURCES.txt
py_expression_lib_opencv.egg-info/dependency_links.txt
py_expression_lib_opencv.egg-info/top_level.txt
py_expression_opencv/__init__.py
py_expression_opencv/lib.py