Metadata-Version: 2.1
Name: py-expression-lib-opencv
Version: 0.0.3
Summary: lib opencv for expressions
Home-page: https://github.com/FlavioLionelRita/py-expression-lib-opencv
Author: Flavio Lionel Rita
Author-email: flaviolrita@hotmail.com
License: UNKNOWN
Download-URL: https://github.com/FlavioLionelRita/py-expression-lib-opencv/tarball/0.0.1
Keywords: opencv,lib,expression
Platform: UNKNOWN
